flixpy/__init__.py
flixpy/browse/__init__.py
flixpy/browse/browse.py
flixpy/constants.py
flixpy/enums/auto_enum.py
flixpy/enums/content_type.py
flixpy/enums/genre.py
flixpy/enums/streaming_provider.py
flixpy/enums/tag.py
flixpy/models/base_content_model.py
flixpy/models/movie.py
flixpy/models/show/episode.py
flixpy/models/show/season.py
flixpy/models/show/show.py
flixpy/models/stream.py
flixpy/models/use_streaming_provider.py
flixpy/utils.py
flixpy-0.0.3.post2.dist-info/WHEEL
flixpy-0.0.3.post2.dist-info/METADATA
flixpy-0.0.3.post2.dist-info/RECORD
