Metadata-Version: 2.1
Name: flixpy
Version: 0.0.3.post2
Summary: 
Home-page: https://github.com/ninest/armorstand/
License: MIT
Author: ninest
Requires-Python: >=3.7.1,<4.0.0
Classifier: License :: OSI Approved :: MIT License
Classifier: Programming Language :: Python :: 3
Classifier: Programming Language :: Python :: 3.8
Classifier: Programming Language :: Python :: 3.9
Requires-Dist: requests (>=2.25.1,<3.0.0)
Project-URL: Documentation, https://github.com/ninest/armorstand/
Project-URL: Repository, https://github.com/ninest/armorstand/
